{"SubTexture":[{"frameHeight":66,"y":701,"frameX":-1,"width":259,"frameY":0,"height":66,"name":"sidailiangdui","frameWidth":261,"x":1},{"frameHeight":66,"y":178,"frameX":-34,"width":192,"frameY":0,"height":65,"name":"sidaier","frameWidth":261,"x":822},{"width":129,"y":245,"height":66,"name":"shuangshun","x":822},{"width":129,"y":381,"height":66,"name":"sanzhang","x":822},{"width":261,"y":713,"height":66,"name":"sandaiyidui","x":510},{"frameHeight":66,"y":701,"frameX":-1,"width":128,"frameY":0,"height":66,"name":"sanshun","frameWidth":129,"x":262},{"width":193,"y":558,"height":65,"name":"sandaiyi","x":1},{"width":129,"y":313,"height":66,"name":"danshun","x":822},{"frameHeight":92,"y":455,"frameX":-20,"width":296,"frameY":-1,"height":88,"name":"nblx_05","frameWidth":322,"x":234},{"frameHeight":272,"y":428,"frameX":-31,"width":17,"frameY":-163,"height":18,"name":"nblizi_15","frameWidth":238,"x":784},{"frameHeight":92,"y":701,"frameX":-10,"width":115,"frameY":-10,"height":69,"name":"nblx_02","frameWidth":322,"x":392},{"frameHeight":92,"y":545,"frameX":-10,"width":61,"frameY":-17,"height":54,"name":"nblx_01","frameWidth":322,"x":510},{"frameHeight":92,"y":628,"frameX":-10,"width":232,"frameY":-3,"height":83,"name":"nblx_04","frameWidth":322,"x":510},{"frameHeight":92,"y":477,"frameX":-10,"width":176,"frameY":-3,"height":79,"name":"nblx_03","frameWidth":322,"x":1},{"width":248,"y":1,"height":248,"name":"nbquan","x":346},{"frameHeight":272,"y":251,"frameX":-4,"width":225,"frameY":-34,"height":202,"name":"nblizi_09","frameWidth":238,"x":346},{"frameHeight":272,"y":428,"frameX":-10,"width":209,"frameY":0,"height":198,"name":"nblizi_13","frameWidth":238,"x":573},{"frameHeight":272,"y":1,"frameX":-56,"width":132,"frameY":-60,"height":175,"name":"nblizi_01","frameWidth":238,"x":822},{"frameHeight":272,"y":1,"frameX":-9,"width":224,"frameY":-57,"height":215,"name":"nblizi_05","frameWidth":238,"x":596},{"frameHeight":272,"y":284,"frameX":-1,"width":231,"frameY":-56,"height":191,"name":"nblizi_07","frameWidth":238,"x":1},{"frameHeight":272,"y":455,"frameX":-35,"width":177,"frameY":-36,"height":213,"name":"nblizi_03","frameWidth":238,"x":784},{"frameHeight":272,"y":218,"frameX":-7,"width":224,"frameY":-8,"height":208,"name":"nblizi_11","frameWidth":238,"x":596},{"width":129,"y":633,"height":66,"name":"feiji","x":330},{"frameHeight":281,"y":1,"frameX":0,"width":343,"frameY":0,"height":281,"name":"fly1","frameWidth":345,"x":1},{"frameHeight":75,"y":633,"frameX":-4,"width":327,"frameY":-4,"height":66,"name":"feijidaichibang","frameWidth":336,"x":1},{"width":274,"y":545,"height":86,"name":"fly4","x":234},{"frameHeight":48,"y":477,"frameX":0,"width":48,"frameY":-1,"height":46,"name":"yan21","frameWidth":48,"x":179},{"frameHeight":48,"y":670,"frameX":0,"width":48,"frameY":-3,"height":41,"name":"yan23","frameWidth":48,"x":744}],"width":1024,"height":1024,"name":"ddz_cardtype_effect","imagePath":"ddz_cardtype_effect_tex.png"}