{"mc":{
	"move":{
		"frameRate":10,
		"labels":[
			{"name":"move","frame":1,"end":8}
			
			],
		"events":[
			
			],
		"frames":[
			
			{
			"res":"ex19_01",
			"x":9,
			"y":7
			},
			{
			"res":"ex19_02",
			"x":9,
			"y":7
			},
			{
			"res":"ex19_03",
			"x":9,
			"y":7
			},
			{
			"res":"ex19_04",
			"x":9,
			"y":7
			},
			{
			"res":"ex19_05",
			"x":9,
			"y":7
			},
			{
			"res":"ex19_06",
			"x":9,
			"y":7
			},
			{
			"res":"ex19_07",
			"x":9,
			"y":7
			},
			{
			"res":"ex19_08",
			"x":9,
			"y":7
			}
			]
}},
	"res":{
		"ex19_02":{"x":91,"y":2,"w":85,"h":89},
		"ex19_07":{"x":91,"y":95,"w":85,"h":89},
		"ex19_06":{"x":91,"y":95,"w":85,"h":89},
		"ex19_01":{"x":2,"y":2,"w":85,"h":89},
		"ex19_08":{"x":91,"y":95,"w":85,"h":89},
		"ex19_04":{"x":2,"y":188,"w":85,"h":89},
		"ex19_05":{"x":2,"y":95,"w":85,"h":89},
		"ex19_03":{"x":2,"y":95,"w":85,"h":89}
	}}