{"frameRate":24,"armature":[{"skin":[{"name":"","slot":[{"display":[{"type":"image","name":"gift03","transform":{}}],"name":"gift03"},{"display":[{"type":"image","name":"gift01_1","transform":{}}],"name":"gift01_1"},{"display":[{"type":"image","name":"gift05","transform":{}}],"name":"gift05"},{"display":[{"type":"image","name":"黄瓜/hg_000","transform":{}},{"type":"image","name":"黄瓜/hg_001","transform":{}},{"type":"image","name":"黄瓜/hg_002","transform":{}},{"type":"image","name":"黄瓜/hg_003","transform":{}},{"type":"image","name":"黄瓜/hg_004","transform":{}},{"type":"image","name":"黄瓜/hg_005","transform":{}},{"type":"image","name":"黄瓜/hg_006","transform":{}},{"type":"image","name":"黄瓜/hg_007","transform":{}},{"type":"image","name":"黄瓜/hg_008","transform":{}}],"name":"hg_000"},{"display":[{"type":"image","name":"玫瑰星星/mgxx_02","transform":{}},{"type":"image","name":"玫瑰星星/mgxx_03","transform":{}},{"type":"image","name":"玫瑰星星/mgxx_04","transform":{}},{"type":"image","name":"玫瑰星星/mgxx_05","transform":{}},{"type":"image","name":"玫瑰星星/mgxx_06","transform":{}},{"type":"image","name":"玫瑰星星/mgxx_07","transform":{}},{"type":"image","name":"玫瑰星星/mgxx_08","transform":{}},{"type":"image","name":"玫瑰星星/mgxx_09","transform":{}},{"type":"image","name":"玫瑰星星/mgxx_10","transform":{}},{"type":"image","name":"玫瑰星星/mgxx_11","transform":{}},{"type":"image","name":"玫瑰星星/mgxx_12","transform":{}},{"type":"image","name":"玫瑰星星/mgxx_13","transform":{}},{"type":"image","name":"玫瑰星星/mgxx_14","transform":{}},{"type":"image","name":"玫瑰星星/mgxx_15","transform":{}}],"name":"mgxx_02"},{"display":[{"type":"image","name":"xbxx","transform":{}}],"name":"xbxx"},{"display":[{"type":"image","name":"gift01_2","transform":{}}],"name":"gift01_2"},{"display":[{"type":"image","name":"gift02","transform":{}}],"name":"gift02"},{"display":[{"type":"image","name":"bz/baozha0001","transform":{}},{"type":"image","name":"bz/baozha0002","transform":{}},{"type":"image","name":"bz/baozha0003","transform":{}},{"type":"image","name":"bz/baozha0004","transform":{}},{"type":"image","name":"bz/baozha0005","transform":{}}],"name":"baozha0001"},{"display":[{"type":"image","name":"gift06_1","transform":{}}],"name":"gift06_1"},{"display":[{"type":"image","name":"gift06_2","transform":{}}],"name":"gift06_2"},{"display":[{"type":"image","name":"气泡/qipao_02","transform":{}},{"type":"image","name":"气泡/qipao_03","transform":{}},{"type":"image","name":"气泡/qipao_04","transform":{}},{"type":"image","name":"气泡/qipao_05","transform":{}},{"type":"image","name":"气泡/qipao_06","transform":{}},{"type":"image","name":"气泡/qipao_07","transform":{}},{"type":"image","name":"气泡/qipao_08","transform":{}},{"type":"image","name":"气泡/qipao_09","transform":{}}],"name":"qipao_02"},{"display":[{"type":"image","name":"gift04","transform":{}}],"name":"gift04"},{"display":[{"type":"image","name":"sui","transform":{}}],"name":"sui"},{"display":[{"type":"image","name":"suizhuan/sz0001","transform":{}},{"type":"image","name":"suizhuan/sz0002","transform":{}},{"type":"image","name":"suizhuan/sz0003","transform":{}},{"type":"image","name":"suizhuan/sz0004","transform":{}},{"type":"image","name":"suizhuan/sz0005","transform":{}},{"type":"image","name":"suizhuan/sz0006","transform":{}},{"type":"image","name":"suizhuan/sz0007","transform":{}}],"name":"sz0001"}]}],"type":"MovieClip","frameRate":24,"slot":[{"color":{},"name":"gift01_2","parent":"gift01_2","displayIndex":-1},{"z":1,"color":{},"name":"gift01_1","parent":"gift01_1","displayIndex":-1},{"z":2,"color":{},"name":"gift02","parent":"gift02","displayIndex":-1},{"z":3,"color":{},"name":"baozha0001","parent":"baozha0001","displayIndex":-1},{"z":4,"color":{},"name":"sui","parent":"sui","displayIndex":-1},{"z":5,"color":{},"name":"gift03","parent":"gift03","displayIndex":-1},{"z":6,"color":{},"name":"sz0001","parent":"sz0001","displayIndex":-1},{"z":7,"color":{},"name":"gift04","parent":"gift04","displayIndex":-1},{"z":8,"color":{},"name":"qipao_02","parent":"qipao_02","displayIndex":-1},{"z":9,"color":{},"name":"xbxx","parent":"xbxx","displayIndex":-1},{"z":10,"color":{},"name":"gift05","parent":"gift05","displayIndex":-1},{"z":11,"color":{},"name":"mgxx_02","parent":"mgxx_02","displayIndex":-1},{"z":12,"color":{},"name":"gift06_2","parent":"gift06_2","displayIndex":-1},{"z":13,"color":{},"name":"gift06_1","parent":"gift06_1","displayIndex":-1},{"z":14,"color":{},"name":"hg_000","parent":"hg_000","displayIndex":-1}],"ik":[],"animation":[{"frame":[],"slot":[{"frame":[{"tweenEasing":0,"duration":10,"color":{}},{"color":{},"duration":10,"curve":[0,0,1,1]},{"tweenEasing":null,"duration":0,"color":{}}],"name":"gift01_1"},{"frame":[{"tweenEasing":null,"duration":20,"color":{}}],"name":"gift01_2"}],"playTimes":0,"ffd":[],"duration":20,"name":"gift2","bone":[{"frame":[{"tweenEasing":null,"duration":20,"transform":{}}],"name":"root"},{"frame":[{"duration":10,"transform":{"y":-13,"x":-12},"curve":[0,0,1,1]},{"duration":10,"transform":{"y":-13,"skX":180,"skY":180,"x":-12},"curve":[0,0,1,1]},{"tweenEasing":null,"duration":0,"transform":{"y":-13,"skX":-1.884,"skY":-1.884,"x":-12}}],"name":"gift01_1"},{"frame":[{"tweenEasing":null,"duration":20,"transform":{"y":26.1028,"x":37.3873}}],"name":"gift01_2"},{"frame":[{"tweenEasing":null,"duration":20,"transform":{}}],"name":"gift02"},{"frame":[{"tweenEasing":null,"duration":20,"transform":{}}],"name":"baozha0001"},{"frame":[{"tweenEasing":null,"duration":20,"transform":{}}],"name":"gift03"},{"frame":[{"tweenEasing":null,"duration":20,"transform":{}}],"name":"sui"},{"frame":[{"tweenEasing":null,"duration":20,"transform":{}}],"name":"sz0001"},{"frame":[{"tweenEasing":null,"duration":20,"transform":{}}],"name":"gift04"},{"frame":[{"tweenEasing":null,"duration":20,"transform":{}}],"name":"qipao_02"},{"frame":[{"tweenEasing":null,"duration":20,"transform":{}}],"name":"xbxx"},{"frame":[{"tweenEasing":null,"duration":20,"transform":{}}],"name":"gift05"},{"frame":[{"tweenEasing":null,"duration":20,"transform":{}}],"name":"mgxx_02"},{"frame":[{"tweenEasing":null,"duration":20,"transform":{}}],"name":"gift06_1"},{"frame":[{"tweenEasing":null,"duration":20,"transform":{}}],"name":"gift06_2"},{"frame":[{"tweenEasing":null,"duration":20,"transform":{}}],"name":"hg_000"}]},{"frame":[],"slot":[{"frame":[{"tweenEasing":null,"duration":2,"color":{}},{"tweenEasing":null,"duration":20,"color":{"aM":0}}],"name":"gift02"},{"frame":[{"tweenEasing":null,"duration":2,"color":{},"displayIndex":-1},{"tweenEasing":null,"duration":1,"color":{}},{"tweenEasing":null,"duration":1,"color":{},"displayIndex":1},{"tweenEasing":null,"duration":1,"color":{},"displayIndex":2},{"tweenEasing":null,"duration":1,"color":{},"displayIndex":3},{"tweenEasing":null,"duration":16,"color":{},"displayIndex":4},{"tweenEasing":null,"duration":0,"color":{},"displayIndex":4}],"name":"baozha0001"}],"playTimes":0,"ffd":[],"duration":22,"name":"gift4","bone":[{"frame":[{"tweenEasing":null,"duration":22,"transform":{}}],"name":"root"},{"frame":[{"tweenEasing":null,"duration":22,"transform":{}}],"name":"gift01_1"},{"frame":[{"tweenEasing":null,"duration":22,"transform":{}}],"name":"gift01_2"},{"frame":[{"tweenEasing":null,"duration":2,"transform":{}},{"tweenEasing":null,"duration":20,"transform":{}}],"name":"gift02"},{"frame":[{"tweenEasing":null,"duration":2,"transform":{}},{"tweenEasing":null,"duration":1,"transform":{}},{"tweenEasing":null,"duration":1,"transform":{}},{"tweenEasing":null,"duration":1,"transform":{}},{"tweenEasing":null,"duration":1,"transform":{}},{"tweenEasing":null,"duration":16,"transform":{}},{"tweenEasing":null,"duration":0,"transform":{}}],"name":"baozha0001"},{"frame":[{"tweenEasing":null,"duration":22,"transform":{}}],"name":"gift03"},{"frame":[{"tweenEasing":null,"duration":22,"transform":{}}],"name":"sui"},{"frame":[{"tweenEasing":null,"duration":22,"transform":{}}],"name":"sz0001"},{"frame":[{"tweenEasing":null,"duration":22,"transform":{}}],"name":"gift04"},{"frame":[{"tweenEasing":null,"duration":22,"transform":{}}],"name":"qipao_02"},{"frame":[{"tweenEasing":null,"duration":22,"transform":{}}],"name":"xbxx"},{"frame":[{"tweenEasing":null,"duration":22,"transform":{}}],"name":"gift05"},{"frame":[{"tweenEasing":null,"duration":22,"transform":{}}],"name":"mgxx_02"},{"frame":[{"tweenEasing":null,"duration":22,"transform":{}}],"name":"gift06_1"},{"frame":[{"tweenEasing":null,"duration":22,"transform":{}}],"name":"gift06_2"},{"frame":[{"tweenEasing":null,"duration":22,"transform":{}}],"name":"hg_000"}]},{"frame":[],"slot":[{"frame":[{"tweenEasing":null,"duration":2,"color":{}},{"tweenEasing":null,"duration":6,"color":{"aM":0}}],"name":"gift03"},{"frame":[{"tweenEasing":null,"duration":1,"color":{},"displayIndex":-1},{"tweenEasing":null,"duration":7,"color":{}}],"name":"sui"},{"frame":[{"tweenEasing":null,"duration":2,"color":{},"displayIndex":-1},{"tweenEasing":null,"duration":1,"color":{}},{"tweenEasing":null,"duration":1,"color":{},"displayIndex":1},{"tweenEasing":null,"duration":1,"color":{},"displayIndex":2},{"tweenEasing":null,"duration":1,"color":{},"displayIndex":3},{"tweenEasing":null,"duration":1,"color":{},"displayIndex":4},{"tweenEasing":null,"duration":1,"color":{},"displayIndex":5},{"tweenEasing":null,"duration":0,"color":{},"displayIndex":6}],"name":"sz0001"}],"playTimes":0,"ffd":[],"duration":8,"name":"gift3","bone":[{"frame":[{"tweenEasing":null,"duration":8,"transform":{}}],"name":"root"},{"frame":[{"tweenEasing":null,"duration":8,"transform":{}}],"name":"gift01_1"},{"frame":[{"tweenEasing":null,"duration":8,"transform":{}}],"name":"gift01_2"},{"frame":[{"tweenEasing":null,"duration":8,"transform":{}}],"name":"gift02"},{"frame":[{"tweenEasing":null,"duration":8,"transform":{}}],"name":"baozha0001"},{"frame":[{"tweenEasing":null,"duration":2,"transform":{}},{"tweenEasing":null,"duration":6,"transform":{}}],"name":"gift03"},{"frame":[{"tweenEasing":null,"duration":1,"transform":{}},{"tweenEasing":null,"duration":7,"transform":{"x":26.8086}}],"name":"sui"},{"frame":[{"tweenEasing":null,"duration":2,"transform":{}},{"tweenEasing":null,"duration":1,"transform":{"y":8,"x":20}},{"tweenEasing":null,"duration":1,"transform":{"y":8,"x":20}},{"tweenEasing":null,"duration":1,"transform":{"y":8,"x":20}},{"tweenEasing":null,"duration":1,"transform":{"y":8,"x":20}},{"tweenEasing":null,"duration":1,"transform":{"y":8,"x":20}},{"tweenEasing":null,"duration":1,"transform":{"y":8,"x":20}},{"tweenEasing":null,"duration":0,"transform":{"y":8,"x":20}}],"name":"sz0001"},{"frame":[{"tweenEasing":null,"duration":8,"transform":{}}],"name":"gift04"},{"frame":[{"tweenEasing":null,"duration":8,"transform":{}}],"name":"qipao_02"},{"frame":[{"tweenEasing":null,"duration":8,"transform":{}}],"name":"xbxx"},{"frame":[{"tweenEasing":null,"duration":8,"transform":{}}],"name":"gift05"},{"frame":[{"tweenEasing":null,"duration":8,"transform":{}}],"name":"mgxx_02"},{"frame":[{"tweenEasing":null,"duration":8,"transform":{}}],"name":"gift06_1"},{"frame":[{"tweenEasing":null,"duration":8,"transform":{}}],"name":"gift06_2"},{"frame":[{"tweenEasing":null,"duration":8,"transform":{}}],"name":"hg_000"}]},{"frame":[],"slot":[{"frame":[{"tweenEasing":null,"duration":24,"color":{}}],"name":"gift04"},{"frame":[{"tweenEasing":null,"duration":2,"color":{}},{"tweenEasing":null,"duration":2,"color":{},"displayIndex":1},{"tweenEasing":null,"duration":2,"color":{},"displayIndex":2},{"tweenEasing":null,"duration":2,"color":{},"displayIndex":3},{"tweenEasing":null,"duration":2,"color":{},"displayIndex":4},{"tweenEasing":null,"duration":2,"color":{},"displayIndex":5},{"tweenEasing":null,"duration":12,"color":{},"displayIndex":6}],"name":"qipao_02"},{"frame":[{"tweenEasing":null,"duration":12,"color":{},"displayIndex":-1},{"tweenEasing":0,"duration":7,"color":{}},{"tweenEasing":0,"duration":5,"color":{}},{"tweenEasing":null,"duration":0,"color":{"aM":0}}],"name":"xbxx"}],"playTimes":0,"ffd":[],"duration":24,"name":"gift5","bone":[{"frame":[{"tweenEasing":null,"duration":24,"transform":{}}],"name":"root"},{"frame":[{"tweenEasing":null,"duration":24,"transform":{}}],"name":"gift01_1"},{"frame":[{"tweenEasing":null,"duration":24,"transform":{}}],"name":"gift01_2"},{"frame":[{"tweenEasing":null,"duration":24,"transform":{}}],"name":"gift02"},{"frame":[{"tweenEasing":null,"duration":24,"transform":{}}],"name":"baozha0001"},{"frame":[{"tweenEasing":null,"duration":24,"transform":{}}],"name":"gift03"},{"frame":[{"tweenEasing":null,"duration":24,"transform":{}}],"name":"sui"},{"frame":[{"tweenEasing":null,"duration":24,"transform":{}}],"name":"sz0001"},{"frame":[{"tweenEasing":null,"duration":24,"transform":{"y":-27,"x":20}}],"name":"gift04"},{"frame":[{"tweenEasing":null,"duration":2,"transform":{}},{"tweenEasing":null,"duration":2,"transform":{}},{"tweenEasing":null,"duration":2,"transform":{}},{"tweenEasing":null,"duration":2,"transform":{}},{"tweenEasing":null,"duration":2,"transform":{}},{"tweenEasing":null,"duration":2,"transform":{}},{"tweenEasing":null,"duration":12,"transform":{}}],"name":"qipao_02"},{"frame":[{"tweenEasing":null,"duration":12,"transform":{}},{"duration":7,"transform":{"scX":0.3301,"y":-51.4299,"scY":0.3301,"x":-8.9873},"curve":[0,0,1,1]},{"duration":5,"transform":{"scX":0.71,"y":-51.4299,"scY":0.71,"skX":90,"skY":90,"x":-8.9873},"curve":[0,0,1,1]},{"tweenEasing":null,"duration":0,"transform":{"scX":0.4632,"y":-51.4299,"scY":0.4632,"skX":180,"skY":180,"x":-8.9873}}],"name":"xbxx"},{"frame":[{"tweenEasing":null,"duration":24,"transform":{}}],"name":"gift05"},{"frame":[{"tweenEasing":null,"duration":24,"transform":{}}],"name":"mgxx_02"},{"frame":[{"tweenEasing":null,"duration":24,"transform":{}}],"name":"gift06_1"},{"frame":[{"tweenEasing":null,"duration":24,"transform":{}}],"name":"gift06_2"},{"frame":[{"tweenEasing":null,"duration":24,"transform":{}}],"name":"hg_000"}]},{"frame":[],"slot":[{"frame":[{"tweenEasing":null,"duration":27,"color":{}}],"name":"gift05"},{"frame":[{"tweenEasing":null,"duration":2,"color":{}},{"tweenEasing":null,"duration":2,"color":{},"displayIndex":1},{"tweenEasing":null,"duration":2,"color":{},"displayIndex":2},{"tweenEasing":null,"duration":2,"color":{},"displayIndex":3},{"tweenEasing":null,"duration":2,"color":{},"displayIndex":4},{"tweenEasing":null,"duration":2,"color":{},"displayIndex":5},{"tweenEasing":null,"duration":2,"color":{},"displayIndex":6},{"tweenEasing":null,"duration":2,"color":{},"displayIndex":7},{"tweenEasing":null,"duration":2,"color":{},"displayIndex":8},{"tweenEasing":null,"duration":2,"color":{},"displayIndex":9},{"tweenEasing":null,"duration":2,"color":{},"displayIndex":10},{"tweenEasing":null,"duration":2,"color":{},"displayIndex":11},{"tweenEasing":null,"duration":2,"color":{},"displayIndex":12},{"tweenEasing":null,"duration":1,"color":{},"displayIndex":13},{"tweenEasing":null,"duration":0,"color":{"aM":0},"displayIndex":13}],"name":"mgxx_02"}],"playTimes":0,"ffd":[],"duration":27,"name":"gift6","bone":[{"frame":[{"tweenEasing":null,"duration":27,"transform":{}}],"name":"root"},{"frame":[{"tweenEasing":null,"duration":27,"transform":{}}],"name":"gift01_1"},{"frame":[{"tweenEasing":null,"duration":27,"transform":{}}],"name":"gift01_2"},{"frame":[{"tweenEasing":null,"duration":27,"transform":{}}],"name":"gift02"},{"frame":[{"tweenEasing":null,"duration":27,"transform":{}}],"name":"baozha0001"},{"frame":[{"tweenEasing":null,"duration":27,"transform":{}}],"name":"gift03"},{"frame":[{"tweenEasing":null,"duration":27,"transform":{}}],"name":"sui"},{"frame":[{"tweenEasing":null,"duration":27,"transform":{}}],"name":"sz0001"},{"frame":[{"tweenEasing":null,"duration":27,"transform":{}}],"name":"gift04"},{"frame":[{"tweenEasing":null,"duration":27,"transform":{}}],"name":"qipao_02"},{"frame":[{"tweenEasing":null,"duration":27,"transform":{}}],"name":"xbxx"},{"frame":[{"tweenEasing":null,"duration":27,"transform":{}}],"name":"gift05"},{"frame":[{"tweenEasing":null,"duration":2,"transform":{"scX":0.8,"scY":0.8}},{"tweenEasing":null,"duration":2,"transform":{"scX":0.8,"scY":0.8}},{"tweenEasing":null,"duration":2,"transform":{"scX":0.8,"scY":0.8}},{"tweenEasing":null,"duration":2,"transform":{"scX":0.8,"scY":0.8}},{"tweenEasing":null,"duration":2,"transform":{"scX":0.8,"scY":0.8}},{"tweenEasing":null,"duration":2,"transform":{"scX":0.8,"scY":0.8}},{"tweenEasing":null,"duration":2,"transform":{"scX":0.8,"scY":0.8}},{"tweenEasing":null,"duration":2,"transform":{"scX":0.8,"scY":0.8}},{"tweenEasing":null,"duration":2,"transform":{"scX":0.8,"scY":0.8}},{"tweenEasing":null,"duration":2,"transform":{"scX":0.8,"scY":0.8}},{"tweenEasing":null,"duration":2,"transform":{"scX":0.8,"scY":0.8}},{"tweenEasing":null,"duration":2,"transform":{"scX":0.8,"scY":0.8}},{"tweenEasing":null,"duration":2,"transform":{"scX":0.8,"scY":0.8}},{"tweenEasing":null,"duration":1,"transform":{"scX":0.8,"scY":0.8}},{"tweenEasing":null,"duration":0,"transform":{}}],"name":"mgxx_02"},{"frame":[{"tweenEasing":null,"duration":27,"transform":{}}],"name":"gift06_1"},{"frame":[{"tweenEasing":null,"duration":27,"transform":{}}],"name":"gift06_2"},{"frame":[{"tweenEasing":null,"duration":27,"transform":{}}],"name":"hg_000"}]},{"frame":[],"slot":[{"frame":[{"tweenEasing":null,"duration":2,"color":{}},{"tweenEasing":null,"duration":2,"color":{},"displayIndex":1},{"tweenEasing":null,"duration":2,"color":{},"displayIndex":2},{"tweenEasing":null,"duration":2,"color":{},"displayIndex":3},{"tweenEasing":null,"duration":2,"color":{},"displayIndex":4},{"tweenEasing":null,"duration":2,"color":{},"displayIndex":5},{"tweenEasing":null,"duration":2,"color":{},"displayIndex":6},{"tweenEasing":null,"duration":2,"color":{},"displayIndex":7},{"tweenEasing":null,"duration":0,"color":{},"displayIndex":8}],"name":"hg_000"}],"playTimes":0,"ffd":[],"duration":16,"name":"gift1","bone":[{"frame":[{"tweenEasing":null,"duration":16,"transform":{}}],"name":"root"},{"frame":[{"tweenEasing":null,"duration":16,"transform":{}}],"name":"gift01_1"},{"frame":[{"tweenEasing":null,"duration":16,"transform":{}}],"name":"gift01_2"},{"frame":[{"tweenEasing":null,"duration":16,"transform":{}}],"name":"gift02"},{"frame":[{"tweenEasing":null,"duration":16,"transform":{}}],"name":"baozha0001"},{"frame":[{"tweenEasing":null,"duration":16,"transform":{}}],"name":"gift03"},{"frame":[{"tweenEasing":null,"duration":16,"transform":{}}],"name":"sui"},{"frame":[{"tweenEasing":null,"duration":16,"transform":{}}],"name":"sz0001"},{"frame":[{"tweenEasing":null,"duration":16,"transform":{}}],"name":"gift04"},{"frame":[{"tweenEasing":null,"duration":16,"transform":{}}],"name":"qipao_02"},{"frame":[{"tweenEasing":null,"duration":16,"transform":{}}],"name":"xbxx"},{"frame":[{"tweenEasing":null,"duration":16,"transform":{}}],"name":"gift05"},{"frame":[{"tweenEasing":null,"duration":16,"transform":{}}],"name":"mgxx_02"},{"frame":[{"tweenEasing":null,"duration":16,"transform":{}}],"name":"gift06_1"},{"frame":[{"tweenEasing":null,"duration":16,"transform":{}}],"name":"gift06_2"},{"frame":[{"tweenEasing":null,"duration":2,"transform":{}},{"tweenEasing":null,"duration":2,"transform":{}},{"tweenEasing":null,"duration":2,"transform":{}},{"tweenEasing":null,"duration":2,"transform":{}},{"tweenEasing":null,"duration":2,"transform":{}},{"tweenEasing":null,"duration":2,"transform":{}},{"tweenEasing":null,"duration":2,"transform":{}},{"tweenEasing":null,"duration":2,"transform":{}},{"tweenEasing":null,"duration":0,"transform":{}}],"name":"hg_000"}]}],"defaultActions":[{"gotoAndPlay":"gift2"}],"aabb":{"width":124.38730000000001,"y":-66.5,"height":112.1028,"x":-65.5},"name":"MovieClip","bone":[{"name":"root","transform":{}},{"transform":{},"name":"gift01_1","parent":"root"},{"transform":{},"name":"gift01_2","parent":"root"},{"transform":{},"name":"gift02","parent":"root"},{"transform":{},"name":"baozha0001","parent":"root"},{"transform":{},"name":"gift03","parent":"root"},{"transform":{},"name":"sui","parent":"root"},{"transform":{},"name":"sz0001","parent":"root"},{"transform":{},"name":"gift04","parent":"root"},{"transform":{},"name":"qipao_02","parent":"root"},{"transform":{},"name":"xbxx","parent":"root"},{"transform":{},"name":"gift05","parent":"root"},{"transform":{},"name":"mgxx_02","parent":"root"},{"transform":{},"name":"gift06_1","parent":"root"},{"transform":{},"name":"gift06_2","parent":"root"},{"transform":{},"name":"hg_000","parent":"root"}]}],"name":"mj_gift_effect_drag","version":"4.5","isGlobal":0}