[
{"cardId":11,"thisId":111,"name":"一万","type":1,"icon":11,"point":1,"nocard":0},
{"cardId":11,"thisId":112,"name":"一万","type":1,"icon":11,"point":1,"nocard":0},
{"cardId":11,"thisId":113,"name":"一万","type":1,"icon":11,"point":1,"nocard":0},
{"cardId":11,"thisId":114,"name":"一万","type":1,"icon":11,"point":1,"nocard":0},
{"cardId":12,"thisId":121,"name":"二万","type":1,"icon":12,"point":2,"nocard":0},
{"cardId":12,"thisId":122,"name":"二万","type":1,"icon":12,"point":2,"nocard":0},
{"cardId":12,"thisId":123,"name":"二万","type":1,"icon":12,"point":2,"nocard":0},
{"cardId":12,"thisId":124,"name":"二万","type":1,"icon":12,"point":2,"nocard":0},
{"cardId":13,"thisId":131,"name":"三万","type":1,"icon":13,"point":3,"nocard":0},
{"cardId":13,"thisId":132,"name":"三万","type":1,"icon":13,"point":3,"nocard":0},
{"cardId":13,"thisId":133,"name":"三万","type":1,"icon":13,"point":3,"nocard":0},
{"cardId":13,"thisId":134,"name":"三万","type":1,"icon":13,"point":3,"nocard":0},
{"cardId":14,"thisId":141,"name":"四万","type":1,"icon":14,"point":4,"nocard":0},
{"cardId":14,"thisId":142,"name":"四万","type":1,"icon":14,"point":4,"nocard":0},
{"cardId":14,"thisId":143,"name":"四万","type":1,"icon":14,"point":4,"nocard":0},
{"cardId":14,"thisId":144,"name":"四万","type":1,"icon":14,"point":4,"nocard":0},
{"cardId":15,"thisId":151,"name":"五万","type":1,"icon":15,"point":5,"nocard":0},
{"cardId":15,"thisId":152,"name":"五万","type":1,"icon":15,"point":5,"nocard":0},
{"cardId":15,"thisId":153,"name":"五万","type":1,"icon":15,"point":5,"nocard":0},
{"cardId":15,"thisId":154,"name":"五万","type":1,"icon":15,"point":5,"nocard":0},
{"cardId":16,"thisId":161,"name":"六万","type":1,"icon":16,"point":6,"nocard":0},
{"cardId":16,"thisId":162,"name":"六万","type":1,"icon":16,"point":6,"nocard":0},
{"cardId":16,"thisId":163,"name":"六万","type":1,"icon":16,"point":6,"nocard":0},
{"cardId":16,"thisId":164,"name":"六万","type":1,"icon":16,"point":6,"nocard":0},
{"cardId":17,"thisId":171,"name":"七万","type":1,"icon":17,"point":7,"nocard":0},
{"cardId":17,"thisId":172,"name":"七万","type":1,"icon":17,"point":7,"nocard":0},
{"cardId":17,"thisId":173,"name":"七万","type":1,"icon":17,"point":7,"nocard":0},
{"cardId":17,"thisId":174,"name":"七万","type":1,"icon":17,"point":7,"nocard":0},
{"cardId":18,"thisId":181,"name":"八万","type":1,"icon":18,"point":8,"nocard":0},
{"cardId":18,"thisId":182,"name":"八万","type":1,"icon":18,"point":8,"nocard":0},
{"cardId":18,"thisId":183,"name":"八万","type":1,"icon":18,"point":8,"nocard":0},
{"cardId":18,"thisId":184,"name":"八万","type":1,"icon":18,"point":8,"nocard":0},
{"cardId":19,"thisId":191,"name":"九万","type":1,"icon":19,"point":9,"nocard":0},
{"cardId":19,"thisId":192,"name":"九万","type":1,"icon":19,"point":9,"nocard":0},
{"cardId":19,"thisId":193,"name":"九万","type":1,"icon":19,"point":9,"nocard":0},
{"cardId":19,"thisId":194,"name":"九万","type":1,"icon":19,"point":9,"nocard":0},
{"cardId":21,"thisId":211,"name":"一条","type":2,"icon":21,"point":1,"nocard":0},
{"cardId":21,"thisId":212,"name":"一条","type":2,"icon":21,"point":1,"nocard":0},
{"cardId":21,"thisId":213,"name":"一条","type":2,"icon":21,"point":1,"nocard":0},
{"cardId":21,"thisId":214,"name":"一条","type":2,"icon":21,"point":1,"nocard":0},
{"cardId":22,"thisId":221,"name":"二条","type":2,"icon":22,"point":2,"nocard":0},
{"cardId":22,"thisId":222,"name":"二条","type":2,"icon":22,"point":2,"nocard":0},
{"cardId":22,"thisId":223,"name":"二条","type":2,"icon":22,"point":2,"nocard":0},
{"cardId":22,"thisId":224,"name":"二条","type":2,"icon":22,"point":2,"nocard":0},
{"cardId":23,"thisId":231,"name":"三条","type":2,"icon":23,"point":3,"nocard":0},
{"cardId":23,"thisId":232,"name":"三条","type":2,"icon":23,"point":3,"nocard":0},
{"cardId":23,"thisId":233,"name":"三条","type":2,"icon":23,"point":3,"nocard":0},
{"cardId":23,"thisId":234,"name":"三条","type":2,"icon":23,"point":3,"nocard":0},
{"cardId":24,"thisId":241,"name":"四条","type":2,"icon":24,"point":4,"nocard":0},
{"cardId":24,"thisId":242,"name":"四条","type":2,"icon":24,"point":4,"nocard":0},
{"cardId":24,"thisId":243,"name":"四条","type":2,"icon":24,"point":4,"nocard":0},
{"cardId":24,"thisId":244,"name":"四条","type":2,"icon":24,"point":4,"nocard":0},
{"cardId":25,"thisId":251,"name":"五条","type":2,"icon":25,"point":5,"nocard":0},
{"cardId":25,"thisId":252,"name":"五条","type":2,"icon":25,"point":5,"nocard":0},
{"cardId":25,"thisId":253,"name":"五条","type":2,"icon":25,"point":5,"nocard":0},
{"cardId":25,"thisId":254,"name":"五条","type":2,"icon":25,"point":5,"nocard":0},
{"cardId":26,"thisId":261,"name":"六条","type":2,"icon":26,"point":6,"nocard":0},
{"cardId":26,"thisId":262,"name":"六条","type":2,"icon":26,"point":6,"nocard":0},
{"cardId":26,"thisId":263,"name":"六条","type":2,"icon":26,"point":6,"nocard":0},
{"cardId":26,"thisId":264,"name":"六条","type":2,"icon":26,"point":6,"nocard":0},
{"cardId":27,"thisId":271,"name":"七条","type":2,"icon":27,"point":7,"nocard":0},
{"cardId":27,"thisId":272,"name":"七条","type":2,"icon":27,"point":7,"nocard":0},
{"cardId":27,"thisId":273,"name":"七条","type":2,"icon":27,"point":7,"nocard":0},
{"cardId":27,"thisId":274,"name":"七条","type":2,"icon":27,"point":7,"nocard":0},
{"cardId":28,"thisId":281,"name":"八条","type":2,"icon":28,"point":8,"nocard":0},
{"cardId":28,"thisId":282,"name":"八条","type":2,"icon":28,"point":8,"nocard":0},
{"cardId":28,"thisId":283,"name":"八条","type":2,"icon":28,"point":8,"nocard":0},
{"cardId":28,"thisId":284,"name":"八条","type":2,"icon":28,"point":8,"nocard":0},
{"cardId":29,"thisId":291,"name":"九条","type":2,"icon":29,"point":9,"nocard":0},
{"cardId":29,"thisId":292,"name":"九条","type":2,"icon":29,"point":9,"nocard":0},
{"cardId":29,"thisId":293,"name":"九条","type":2,"icon":29,"point":9,"nocard":0},
{"cardId":29,"thisId":294,"name":"九条","type":2,"icon":29,"point":9,"nocard":0},
{"cardId":31,"thisId":311,"name":"一筒","type":3,"icon":31,"point":1,"nocard":0},
{"cardId":31,"thisId":312,"name":"一筒","type":3,"icon":31,"point":1,"nocard":0},
{"cardId":31,"thisId":313,"name":"一筒","type":3,"icon":31,"point":1,"nocard":0},
{"cardId":31,"thisId":314,"name":"一筒","type":3,"icon":31,"point":1,"nocard":0},
{"cardId":32,"thisId":321,"name":"二筒","type":3,"icon":32,"point":2,"nocard":0},
{"cardId":32,"thisId":322,"name":"二筒","type":3,"icon":32,"point":2,"nocard":0},
{"cardId":32,"thisId":323,"name":"二筒","type":3,"icon":32,"point":2,"nocard":0},
{"cardId":32,"thisId":324,"name":"二筒","type":3,"icon":32,"point":2,"nocard":0},
{"cardId":33,"thisId":331,"name":"三筒","type":3,"icon":33,"point":3,"nocard":0},
{"cardId":33,"thisId":332,"name":"三筒","type":3,"icon":33,"point":3,"nocard":0},
{"cardId":33,"thisId":333,"name":"三筒","type":3,"icon":33,"point":3,"nocard":0},
{"cardId":33,"thisId":334,"name":"三筒","type":3,"icon":33,"point":3,"nocard":0},
{"cardId":34,"thisId":341,"name":"四筒","type":3,"icon":34,"point":4,"nocard":0},
{"cardId":34,"thisId":342,"name":"四筒","type":3,"icon":34,"point":4,"nocard":0},
{"cardId":34,"thisId":343,"name":"四筒","type":3,"icon":34,"point":4,"nocard":0},
{"cardId":34,"thisId":344,"name":"四筒","type":3,"icon":34,"point":4,"nocard":0},
{"cardId":35,"thisId":351,"name":"五筒","type":3,"icon":35,"point":5,"nocard":0},
{"cardId":35,"thisId":352,"name":"五筒","type":3,"icon":35,"point":5,"nocard":0},
{"cardId":35,"thisId":353,"name":"五筒","type":3,"icon":35,"point":5,"nocard":0},
{"cardId":35,"thisId":354,"name":"五筒","type":3,"icon":35,"point":5,"nocard":0},
{"cardId":36,"thisId":361,"name":"六筒","type":3,"icon":36,"point":6,"nocard":0},
{"cardId":36,"thisId":362,"name":"六筒","type":3,"icon":36,"point":6,"nocard":0},
{"cardId":36,"thisId":363,"name":"六筒","type":3,"icon":36,"point":6,"nocard":0},
{"cardId":36,"thisId":364,"name":"六筒","type":3,"icon":36,"point":6,"nocard":0},
{"cardId":37,"thisId":371,"name":"七筒","type":3,"icon":37,"point":7,"nocard":0},
{"cardId":37,"thisId":372,"name":"七筒","type":3,"icon":37,"point":7,"nocard":0},
{"cardId":37,"thisId":373,"name":"七筒","type":3,"icon":37,"point":7,"nocard":0},
{"cardId":37,"thisId":374,"name":"七筒","type":3,"icon":37,"point":7,"nocard":0},
{"cardId":38,"thisId":381,"name":"八筒","type":3,"icon":38,"point":8,"nocard":0},
{"cardId":38,"thisId":382,"name":"八筒","type":3,"icon":38,"point":8,"nocard":0},
{"cardId":38,"thisId":383,"name":"八筒","type":3,"icon":38,"point":8,"nocard":0},
{"cardId":38,"thisId":384,"name":"八筒","type":3,"icon":38,"point":8,"nocard":0},
{"cardId":39,"thisId":391,"name":"九筒","type":3,"icon":39,"point":9,"nocard":0},
{"cardId":39,"thisId":392,"name":"九筒","type":3,"icon":39,"point":9,"nocard":0},
{"cardId":39,"thisId":393,"name":"九筒","type":3,"icon":39,"point":9,"nocard":0},
{"cardId":39,"thisId":394,"name":"九筒","type":3,"icon":39,"point":9,"nocard":0},
{"cardId":41,"thisId":411,"name":"东风","type":4,"icon":41,"point":1,"nocard":0},
{"cardId":41,"thisId":412,"name":"东风","type":4,"icon":41,"point":1,"nocard":0},
{"cardId":41,"thisId":413,"name":"东风","type":4,"icon":41,"point":1,"nocard":0},
{"cardId":41,"thisId":414,"name":"东风","type":4,"icon":41,"point":1,"nocard":0},
{"cardId":42,"thisId":421,"name":"南风","type":4,"icon":42,"point":2,"nocard":0},
{"cardId":42,"thisId":422,"name":"南风","type":4,"icon":42,"point":2,"nocard":0},
{"cardId":42,"thisId":423,"name":"南风","type":4,"icon":42,"point":2,"nocard":0},
{"cardId":42,"thisId":424,"name":"南风","type":4,"icon":42,"point":2,"nocard":0},
{"cardId":43,"thisId":431,"name":"西风","type":4,"icon":43,"point":3,"nocard":0},
{"cardId":43,"thisId":432,"name":"西风","type":4,"icon":43,"point":3,"nocard":0},
{"cardId":43,"thisId":433,"name":"西风","type":4,"icon":43,"point":3,"nocard":0},
{"cardId":43,"thisId":434,"name":"西风","type":4,"icon":43,"point":3,"nocard":0},
{"cardId":44,"thisId":441,"name":"北风","type":4,"icon":44,"point":4,"nocard":0},
{"cardId":44,"thisId":442,"name":"北风","type":4,"icon":44,"point":4,"nocard":0},
{"cardId":44,"thisId":443,"name":"北风","type":4,"icon":44,"point":4,"nocard":0},
{"cardId":44,"thisId":444,"name":"北风","type":4,"icon":44,"point":4,"nocard":0},
{"cardId":45,"thisId":451,"name":"红中","type":4,"icon":45,"point":5,"nocard":0},
{"cardId":45,"thisId":452,"name":"红中","type":4,"icon":45,"point":5,"nocard":0},
{"cardId":45,"thisId":453,"name":"红中","type":4,"icon":45,"point":5,"nocard":0},
{"cardId":45,"thisId":454,"name":"红中","type":4,"icon":45,"point":5,"nocard":0},
{"cardId":46,"thisId":461,"name":"发财","type":4,"icon":46,"point":6,"nocard":0},
{"cardId":46,"thisId":462,"name":"发财","type":4,"icon":46,"point":6,"nocard":0},
{"cardId":46,"thisId":463,"name":"发财","type":4,"icon":46,"point":6,"nocard":0},
{"cardId":46,"thisId":464,"name":"发财","type":4,"icon":46,"point":6,"nocard":0},
{"cardId":47,"thisId":471,"name":"白板","type":4,"icon":47,"point":7,"nocard":0},
{"cardId":47,"thisId":472,"name":"白板","type":4,"icon":47,"point":7,"nocard":0},
{"cardId":47,"thisId":473,"name":"白板","type":4,"icon":47,"point":7,"nocard":0},
{"cardId":47,"thisId":474,"name":"白板","type":4,"icon":47,"point":7,"nocard":0},
{"cardId":48,"thisId":481,"name":"春","type":4,"icon":51,"point":8,"nocard":1},
{"cardId":48,"thisId":482,"name":"夏","type":4,"icon":52,"point":8,"nocard":1},
{"cardId":48,"thisId":483,"name":"秋","type":4,"icon":53,"point":8,"nocard":1},
{"cardId":48,"thisId":484,"name":"冬","type":4,"icon":54,"point":8,"nocard":1},
{"cardId":48,"thisId":485,"name":"梅","type":4,"icon":55,"point":8,"nocard":1},
{"cardId":48,"thisId":486,"name":"兰","type":4,"icon":56,"point":8,"nocard":1},
{"cardId":48,"thisId":487,"name":"竹","type":4,"icon":57,"point":8,"nocard":1},
{"cardId":48,"thisId":488,"name":"菊","type":4,"icon":58,"point":8,"nocard":1},
{"cardId":51,"thisId":511,"name":"春","type":5,"icon":51,"point":1,"nocard":0},
{"cardId":52,"thisId":521,"name":"夏","type":5,"icon":52,"point":2,"nocard":0},
{"cardId":53,"thisId":531,"name":"秋","type":5,"icon":53,"point":3,"nocard":0},
{"cardId":54,"thisId":541,"name":"冬","type":5,"icon":54,"point":4,"nocard":0},
{"cardId":55,"thisId":551,"name":"梅","type":5,"icon":55,"point":5,"nocard":0},
{"cardId":56,"thisId":561,"name":"兰","type":5,"icon":56,"point":6,"nocard":0},
{"cardId":57,"thisId":571,"name":"竹","type":5,"icon":57,"point":7,"nocard":0},
{"cardId":58,"thisId":581,"name":"菊","type":5,"icon":58,"point":8,"nocard":0},
{"cardId":59,"thisId":591,"name":"红中","type":5,"icon":45,"point":9,"nocard":1},
{"cardId":59,"thisId":592,"name":"红中","type":5,"icon":45,"point":9,"nocard":1},
{"cardId":59,"thisId":593,"name":"红中","type":5,"icon":45,"point":9,"nocard":1},
{"cardId":59,"thisId":594,"name":"红中","type":5,"icon":45,"point":9,"nocard":1}
]
